setup.py
mudpy/__init__.py
mudpy/containers.py
mudpy/global_variables.py
mudpy/mcomment.py
mudpy/mcontainer.py
mudpy/mdata.py
mudpy/mdict.py
mudpy/mhist.py
mudpy/mlist.py
mudpy/mscaler.py
mudpy/mvar.py
mud_py-1.2.11.dist-info/METADATA
mud_py-1.2.11.dist-info/WHEEL
mud_py-1.2.11.dist-info/licenses/LICENSE
mud_py-1.2.11.dist-info/RECORD
