Metadata-Version: 2.1
Name: mud-py
Version: 1.2.11
Summary: MUon Data file reader
Project-URL: Homepage, https://github.com/dfujim/mudpy
Project-URL: Bug Tracker, https://github.com/dfujim/mudpy/issues
Author-email: Derek Fujimoto <dfujimoto@triumf.ca>
License:                     GNU GENERAL PUBLIC LICENSE
License-File: LICENSE
Classifier: Development Status :: 5 - Production/Stable
Classifier: License :: OSI Approved :: GNU Lesser General Public License v3 (LGPLv3)
Classifier: Operating System :: MacOS
Classifier: Operating System :: Microsoft :: Windows
Classifier: Operating System :: POSIX :: Linux
Classifier: Programming Language :: Cython
Classifier: Programming Language :: Python
Classifier: Programming Language :: Python :: 3.7
Requires-Python: >=3.7
Requires-Dist: numpy>=1.19
